{"level": {"id": 28, "size": {"width": 10, "height": 11}, "words": [{"answer": "IMBUE", "isHorizontal": false, "pos": {"x": 0, "y": 3}, "question": "Penetrate"}, {"answer": "DASH", "isHorizontal": false, "pos": {"x": 0, "y": 8}, "question": "Small amount \u0421 move fast"}, {"answer": "ERGO", "isHorizontal": false, "pos": {"x": 1, "y": 0}, "question": "Consequently"}, {"answer": "EXAM", "isHorizontal": true, "pos": {"x": 1, "y": 0}, "question": "School test"}, {"answer": "LASHED", "isHorizontal": false, "pos": {"x": 2, "y": 5}, "question": "Tied \u0421 beaten"}, {"answer": "LAPSE", "isHorizontal": true, "pos": {"x": 2, "y": 5}, "question": "Retrogress"}, {"answer": "ORDERS", "isHorizontal": true, "pos": {"x": 4, "y": 0}, "question": "Commands"}, {"answer": "REPENT", "isHorizontal": false, "pos": {"x": 4, "y": 1}, "question": "Be contrite"}, {"answer": "YELLED", "isHorizontal": true, "pos": {"x": 6, "y": 4}, "question": "Shouted"}, {"answer": "EERIE", "isHorizontal": false, "pos": {"x": 6, "y": 8}, "question": "Creepy"}, {"answer": "INLET", "isHorizontal": true, "pos": {"x": 8, "y": 0}, "question": "Opening through which fluid can pass"}, {"answer": "NOMINEE", "isHorizontal": true, "pos": {"x": 10, "y": 2}, "question": "Person put up for a post"}]}}